{"metadata": {"dbt_schema_version": "https://schemas.getdbt.com/dbt/run-results/v4.json", "dbt_version": "1.3.1", "generated_at": "2022-12-17T23:49:01.714636Z", "invocation_id": "8f97d4d3-7aa9-4b0a-9f28-85e3910bc82f", "env": {}}, "results": [{"status": "success", "timing": [{"name": "compile", "started_at": "2022-12-17T23:48:42.297746Z", "completed_at": "2022-12-17T23:48:42.335356Z"}, {"name": "execute", "started_at": "2022-12-17T23:48:42.338368Z", "completed_at": "2022-12-17T23:48:43.269639Z"}], "thread_id": "Thread-1", "execution_time": 0.9718930721282959, "adapter_response": {"_message": "CREATE VIEW (0 processed)", "code": "CREATE VIEW", "bytes_processed": 0, "location": "US", "project_id": "arched-router-371901", "job_id": "038305b4-b004-475f-beb4-d18bcf0aa466", "slot_ms": 0}, "message": "CREATE VIEW (0 processed)", "failures": null, "unique_id": "model.jaffle_shop_metrics.stg_customers"}, {"status": "success", "timing": [{"name": "compile", "started_at": "2022-12-17T23:48:43.283798Z", "completed_at": "2022-12-17T23:48:43.290796Z"}, {"name": "execute", "started_at": "2022-12-17T23:48:43.291798Z", "completed_at": "2022-12-17T23:48:44.213228Z"}], "thread_id": "Thread-1", "execution_time": 0.9304318428039551, "adapter_response": {"_message": "CREATE VIEW (0 processed)", "code": "CREATE VIEW", "bytes_processed": 0, "location": "US", "project_id": "arched-router-371901", "job_id": "07195bdc-3fd3-44d9-8a4e-afbb01c1c548", "slot_ms": 0}, "message": "CREATE VIEW (0 processed)", "failures": null, "unique_id": "model.jaffle_shop_metrics.stg_orders"}, {"status": "success", "timing": [{"name": "compile", "started_at": "2022-12-17T23:48:44.235371Z", "completed_at": "2022-12-17T23:48:44.248370Z"}, {"name": "execute", "started_at": "2022-12-17T23:48:44.249552Z", "completed_at": "2022-12-17T23:48:45.073432Z"}], "thread_id": "Thread-1", "execution_time": 0.8410990238189697, "adapter_response": {"_message": "CREATE VIEW (0 processed)", "code": "CREATE VIEW", "bytes_processed": 0, "location": "US", "project_id": "arched-router-371901", "job_id": "db908b3e-f009-4f06-b050-43ef322b87b0", "slot_ms": 0}, "message": "CREATE VIEW (0 processed)", "failures": null, "unique_id": "model.jaffle_shop_metrics.stg_payments"}, {"status": "success", "timing": [{"name": "compile", "started_at": "2022-12-17T23:48:45.099029Z", "completed_at": "2022-12-17T23:48:46.217189Z"}, {"name": "execute", "started_at": "2022-12-17T23:48:46.217189Z", "completed_at": "2022-12-17T23:48:49.997506Z"}], "thread_id": "Thread-1", "execution_time": 4.901974678039551, "adapter_response": {"_message": "CREATE TABLE (14.6k rows, 0 processed)", "code": "CREATE TABLE", "rows_affected": 14610, "bytes_processed": 0, "location": "US", "project_id": "arched-router-371901", "job_id": "f189a327-3868-4de3-a39d-6b7d80e60338", "slot_ms": 5950}, "message": "CREATE TABLE (14.6k rows, 0 processed)", "failures": null, "unique_id": "model.metrics.dbt_metrics_default_calendar"}, {"status": "success", "timing": [{"name": "compile", "started_at": "2022-12-17T23:48:50.030578Z", "completed_at": "2022-12-17T23:48:50.048533Z"}, {"name": "execute", "started_at": "2022-12-17T23:48:50.050539Z", "completed_at": "2022-12-17T23:48:52.759588Z"}], "thread_id": "Thread-1", "execution_time": 2.734041452407837, "adapter_response": {"_message": "CREATE TABLE (100.0 rows, 4.3 KB processed)", "code": "CREATE TABLE", "rows_affected": 100, "bytes_processed": 4362, "location": "US", "project_id": "arched-router-371901", "job_id": "6f1e84d6-9807-4e38-b3fa-7d961a78096d", "slot_ms": 11036}, "message": "CREATE TABLE (100.0 rows, 4.3 KB processed)", "failures": null, "unique_id": "model.jaffle_shop_metrics.int_customer_order_history_joined"}, {"status": "success", "timing": [{"name": "compile", "started_at": "2022-12-17T23:48:52.775982Z", "completed_at": "2022-12-17T23:48:52.780154Z"}, {"name": "execute", "started_at": "2022-12-17T23:48:52.780154Z", "completed_at": "2022-12-17T23:48:55.567429Z"}], "thread_id": "Thread-1", "execution_time": 2.792288064956665, "adapter_response": {"_message": "CREATE TABLE (99.0 rows, 6.5 KB processed)", "code": "CREATE TABLE", "rows_affected": 99, "bytes_processed": 6660, "location": "US", "project_id": "arched-router-371901", "job_id": "18986a25-5a86-4f2b-8afc-67263a8d965e", "slot_ms": 9091}, "message": "CREATE TABLE (99.0 rows, 6.5 KB processed)", "failures": null, "unique_id": "model.jaffle_shop_metrics.int_order_payments_pivoted"}, {"status": "success", "timing": [{"name": "compile", "started_at": "2022-12-17T23:48:55.583372Z", "completed_at": "2022-12-17T23:48:55.977038Z"}, {"name": "execute", "started_at": "2022-12-17T23:48:55.977038Z", "completed_at": "2022-12-17T23:48:58.690458Z"}], "thread_id": "Thread-1", "execution_time": 3.1230287551879883, "adapter_response": {"_message": "CREATE TABLE (4.0 rows, 229.8 KB processed)", "code": "CREATE TABLE", "rows_affected": 4, "bytes_processed": 235344, "location": "US", "project_id": "arched-router-371901", "job_id": "42990794-8ba3-4a0d-9c22-c4a2a37dcf38", "slot_ms": 6327}, "message": "CREATE TABLE (4.0 rows, 229.8 KB processed)", "failures": null, "unique_id": "model.jaffle_shop_metrics.example_develop_metric"}, {"status": "success", "timing": [{"name": "compile", "started_at": "2022-12-17T23:48:58.715597Z", "completed_at": "2022-12-17T23:48:58.717963Z"}, {"name": "execute", "started_at": "2022-12-17T23:48:58.717963Z", "completed_at": "2022-12-17T23:49:01.629107Z"}], "thread_id": "Thread-1", "execution_time": 2.917513608932495, "adapter_response": {"_message": "CREATE TABLE (99.0 rows, 11.9 KB processed)", "code": "CREATE TABLE", "rows_affected": 99, "bytes_processed": 12208, "location": "US", "project_id": "arched-router-371901", "job_id": "72fe3584-10dc-4178-8503-3a3a3b04cf1c", "slot_ms": 2819}, "message": "CREATE TABLE (99.0 rows, 11.9 KB processed)", "failures": null, "unique_id": "model.jaffle_shop_metrics.orders"}], "elapsed_time": 20.102394819259644, "args": {"write_json": true, "use_colors": true, "printer_width": 80, "version_check": true, "partial_parse": true, "static_parser": true, "profiles_dir": "C:\\Users\\lliu9\\.dbt", "send_anonymous_usage_stats": true, "event_buffer_size": 100000, "quiet": false, "no_print": false, "which": "run", "rpc_method": "run", "indirect_selection": "eager"}}